fetch_gitignore/__init__.py
fetch_gitignore/core.py
fetch_gitignore-0.4.0.dist-info/METADATA
fetch_gitignore-0.4.0.dist-info/WHEEL
fetch_gitignore-0.4.0.dist-info/entry_points.txt
fetch_gitignore-0.4.0.dist-info/top_level.txt
fetch_gitignore-0.4.0.dist-info/RECORD
